xarizmi/__init__.py
xarizmi/candlestick.py
xarizmi/config.py
xarizmi/enums.py
xarizmi/py.typed
xarizmi/db/__init__.py
xarizmi/db/admin.py
xarizmi/db/alembic.ini
xarizmi/db/client.py
xarizmi/db/actions/__init__.py
xarizmi/db/actions/exchange.py
xarizmi/db/actions/symbol.py
xarizmi/db/actions/candlestick/__init__.py
xarizmi/db/actions/candlestick/candlestick.py
xarizmi/db/actions/candlestick/candlestick_read.py
xarizmi/db/actions/order/__init__.py
xarizmi/db/actions/order/delete.py
xarizmi/db/actions/order/read.py
xarizmi/db/actions/order/upsert.py
xarizmi/db/actions/portfolio/__init__.py
xarizmi/db/actions/portfolio/portfolio_create.py
xarizmi/db/actions/portfolio/portfolio_read.py
xarizmi/db/admin_tools/__init__.py
xarizmi/db/admin_tools/export.py
xarizmi/db/admin_tools/load.py
xarizmi/db/alembic/__init__.py
xarizmi/db/alembic/env.py
xarizmi/db/alembic/script.py.mako
xarizmi/db/alembic/versions/0f106fabd22f_add_more_fields.py
xarizmi/db/alembic/versions/258ee56e7873_add_uniqueness_constraints_on_exchange.py
xarizmi/db/alembic/versions/40610635cc37_add_order_model.py
xarizmi/db/alembic/versions/4bcb140de81f_first_migrations.py
xarizmi/db/alembic/versions/__init__.py
xarizmi/db/alembic/versions/c63cb9ba06b2_add_portfolio_model.py
xarizmi/db/alembic/versions/dfe454fc4858_fix_columns_type_buy_in_candlestick.py
xarizmi/db/alembic/versions/e33464855650_update_interval_type.py
xarizmi/db/alembic/versions/e726c627ded5_add_uniqueness_constraints.py
xarizmi/db/mappers/__init__.py
xarizmi/db/mappers/base.py
xarizmi/db/mappers/symbol.py
xarizmi/db/models/__init__.py
xarizmi/db/models/base.py
xarizmi/db/models/candlestick.py
xarizmi/db/models/constants.py
xarizmi/db/models/exchange.py
xarizmi/db/models/order.py
xarizmi/db/models/portfolio.py
xarizmi/db/models/symbol.py
xarizmi/examples/__init__.py
xarizmi/examples/download_yahoo_finance_data.py
xarizmi/examples/example_with_db.py
xarizmi/examples/candlesticks/__init__.py
xarizmi-0.10.4.dist-info/LICENSE
xarizmi-0.10.4.dist-info/METADATA
xarizmi-0.10.4.dist-info/WHEEL
xarizmi-0.10.4.dist-info/top_level.txt
xarizmi-0.10.4.dist-info/RECORD
