Metadata-Version: 2.1
Name: xarizmi
Version: 0.10.4
Summary: Xarizmi (read Khwarizmi) project is an educational project thatcontains tools for technical analysis in Python.
Home-page: https://github.com/javadebadi/xarizmi
Author: Javad Ebadi
Author-email: javad@javadebadi.com
License: Apache 2.0
Requires-Python: >=3.11
License-File: LICENSE
Requires-Dist: pydantic ==2.7.0
Requires-Dist: scipy >=1.13.1
Requires-Dist: numpy ~=1.24
Requires-Dist: mplfinance
Requires-Dist: matplotlib
Requires-Dist: yfinance ~=0.2
Requires-Dist: TA-Lib
Requires-Dist: alembic >=1.13.1
Requires-Dist: SQLAlchemy >=2.0.30
